<?xml version="1.0" encoding="UTF-8"?>
<objects serializationModel="Studio.02.02.00">
	<object class="AudioFile" id="{5718be8a-8b5e-4fa5-86aa-6d29b696e4fe}">
		<property name="assetPath">
			<value>SFX/char/PostStep/Wood/S_Wood10.wav</value>
		</property>
		<property name="frequencyInKHz">
			<value>96</value>
		</property>
		<property name="channelCount">
			<value>2</value>
		</property>
		<property name="length">
			<value>0.42573958333333334</value>
		</property>
		<relationship name="masterAssetFolder">
			<destination>{542ff4ed-1b88-4c2c-98cc-a4f4c45c5308}</destination>
		</relationship>
	</object>
</objects>
