<?xml version="1.0" encoding="UTF-8"?>
<objects serializationModel="Studio.02.02.00">
	<object class="AudioFile" id="{97cc33dd-e590-4e96-b3e8-484eff5b8bfb}">
		<property name="assetPath">
			<value>IR/03 Number 3 Covered Slip/03a-#3Mezz-KM184-CentreInwards-BURST.wav</value>
		</property>
		<property name="frequencyInKHz">
			<value>48</value>
		</property>
		<property name="channelCount">
			<value>2</value>
		</property>
		<property name="length">
			<value>3.5293749999999999</value>
		</property>
		<relationship name="masterAssetFolder">
			<destination>{542ff4ed-1b88-4c2c-98cc-a4f4c45c5308}</destination>
		</relationship>
	</object>
</objects>
