<?xml version="1.0" encoding="UTF-8"?>
<objects serializationModel="Studio.02.02.00">
	<object class="AudioFile" id="{d898c810-e558-4b1c-b9ba-e85989f4c951}">
		<property name="assetPath">
			<value>SFX/char/enemy/eye/spawn/Glitch 26-MO_KVRI_snare_scream.wav</value>
		</property>
		<property name="frequencyInKHz">
			<value>44.0999985</value>
		</property>
		<property name="channelCount">
			<value>2</value>
		</property>
		<property name="length">
			<value>0.59999999999999998</value>
		</property>
		<relationship name="masterAssetFolder">
			<destination>{542ff4ed-1b88-4c2c-98cc-a4f4c45c5308}</destination>
		</relationship>
	</object>
</objects>
